antares/craft/__init__.py
antares/craft/py.typed
antares/craft/api_conf/__init__.py
antares/craft/api_conf/api_conf.py
antares/craft/api_conf/request_wrapper.py
antares/craft/config/__init__.py
antares/craft/config/base_configuration.py
antares/craft/config/local_configuration.py
antares/craft/exceptions/__init__.py
antares/craft/exceptions/exceptions.py
antares/craft/model/__init__.py
antares/craft/model/area.py
antares/craft/model/binding_constraint.py
antares/craft/model/cluster.py
antares/craft/model/commons.py
antares/craft/model/hydro.py
antares/craft/model/link.py
antares/craft/model/output.py
antares/craft/model/renewable.py
antares/craft/model/scenario_builder.py
antares/craft/model/simulation.py
antares/craft/model/st_storage.py
antares/craft/model/study.py
antares/craft/model/thermal.py
antares/craft/model/settings/__init__.py
antares/craft/model/settings/adequacy_patch.py
antares/craft/model/settings/advanced_parameters.py
antares/craft/model/settings/general.py
antares/craft/model/settings/optimization.py
antares/craft/model/settings/playlist_parameters.py
antares/craft/model/settings/study_settings.py
antares/craft/model/settings/thematic_trimming.py
antares/craft/model/xpansion/__init__.py
antares/craft/model/xpansion/candidate.py
antares/craft/model/xpansion/constraint.py
antares/craft/model/xpansion/sensitivity.py
antares/craft/model/xpansion/settings.py
antares/craft/model/xpansion/xpansion_configuration.py
antares/craft/service/__init__.py
antares/craft/service/base_services.py
antares/craft/service/utils.py
antares/craft/service/xpansion_output_parsing.py
antares/craft/service/api_services/__init__.py
antares/craft/service/api_services/factory.py
antares/craft/service/api_services/utils.py
antares/craft/service/api_services/models/__init__.py
antares/craft/service/api_services/models/area.py
antares/craft/service/api_services/models/base_model.py
antares/craft/service/api_services/models/binding_constraint.py
antares_craft-0.9.5.dist-info/licenses/AUTHORS.txt
antares_craft-0.9.5.dist-info/licenses/LICENSE
antares_craft-0.9.5.dist-info/METADATA
antares_craft-0.9.5.dist-info/WHEEL
antares_craft-0.9.5.dist-info/top_level.txt
antares_craft-0.9.5.dist-info/RECORD
