Metadata-Version: 2.4
Name: antares_craft
Version: 0.9.5
Summary: Python library to read, edit and launch antares-simulator studies
Author: Sylvain Leclerc, Tatiana Vargas, Martin Belthle, Sigurd Borge
License: Mozilla Public License Version 2.0
Project-URL: Repository, https://github.com/AntaresSimulatorTeam/antares_craft
Project-URL: Bug Tracker, https://github.com/AntaresSimulatorTeam/antares_craft/issues
Classifier: Development Status :: 2 - Pre-Alpha
Classifier: License :: OSI Approved :: Mozilla Public License 2.0 (MPL 2.0)
Classifier: Programming Language :: Python :: 3.10
Classifier: Programming Language :: Python :: 3.11
Classifier: Programming Language :: Python :: 3.12
Classifier: Programming Language :: Python :: 3.13
Classifier: Programming Language :: Python :: 3.14
Requires-Python: >=3.10
License-File: LICENSE
License-File: AUTHORS.txt
Requires-Dist: antares-timeseries-generation==0.1.9
Requires-Dist: antares-study-version==1.0.20
Requires-Dist: numpy<3.0.0,>=2.0.0
Requires-Dist: pandas<3.0.0,>=2.0.0
Requires-Dist: pyarrow<30.0.0,>=22.0.0
Requires-Dist: pydantic<3.0.0,>=2.0.0
Requires-Dist: requests<3.0.0,>=2.0.0
Requires-Dist: psutil<8.0.0,>=7.0.0
Requires-Dist: polars>=1.35.0
Dynamic: license-file
